cryptoschema_extractor/__init__.py
cryptoschema_extractor/main.py
cryptoschema_extractor/prompts.py
cryptoschema_extractor-2025.12.21112205.dist-info/METADATA
cryptoschema_extractor-2025.12.21112205.dist-info/WHEEL
cryptoschema_extractor-2025.12.21112205.dist-info/top_level.txt
cryptoschema_extractor-2025.12.21112205.dist-info/RECORD
