Metadata-Version: 2.4
Name: cryptoschema-extractor
Version: 2025.12.21112205
Summary: This system takes a textual synopsis of a cryptographic scheme and extracts a structured summary that highlights its key components, such as the types of finite fields used, the encryption process, ke
Author-email: cryptoschema-extractor <hi@eugene.plus>
License: MIT
Project-URL: Homepage, https://github.com/chigwell/cryptoschema-extractor
Requires-Python: >=3.9
Requires-Dist: langchain-llm7>=0.0.0
Requires-Dist: llmatch-messages>=0.0.0
Requires-Dist: langchain-core>=0.3.0
